{
  "project_info": {
    "project_number": "1031195011907",
    "project_id": "database-app-10207",
    "storage_bucket": "database-app-10207.appspot.com"
  },
  "client": [
    {
      "client_info": {
        "mobilesdk_app_id": "1:1031195011907:android:f05ab795d747e4bc459df6",
        "android_client_info": {
          "package_name": "com.databaseapp"
        }
      },
      "oauth_client": [
        {
          "client_id": "1031195011907-qbif41mmjgragruugokqjspn0p9b4o30.apps.googleusercontent.com",
          "client_type": 3
        }
      ],
      "api_key": [
        {
          "current_key": "AIzaSyBDRRBmPQTuf-khFdmT1Sdm6Vc2brCw0hg"
        }
      ],
      "services": {
        "appinvite_service": {
          "other_platform_oauth_client": [
            {
              "client_id": "1031195011907-qbif41mmjgragruugokqjspn0p9b4o30.apps.googleusercontent.com",
              "client_type": 3
            }
          ]
        }
      }
    }
  ],
  "configuration_version": "1"
}